isaac_martin_sdk/__init__.py
isaac_martin_sdk/filter.py
isaac_martin_sdk/resources/__init__.py
isaac_martin_sdk/resources/base_resource.py
isaac_martin_sdk/resources/book.py
isaac_martin_sdk/resources/chapter.py
isaac_martin_sdk/resources/character.py
isaac_martin_sdk/resources/movie.py
isaac_martin_sdk/resources/quote.py
isaac_martin_sdk/sdk.py
isaac_martin_sdk/sdk_config.py
isaac_martin_sdk-0.1.3.dist-info/WHEEL
isaac_martin_sdk-0.1.3.dist-info/METADATA
isaac_martin_sdk-0.1.3.dist-info/RECORD
